pyfaktory/__init__.py
pyfaktory/client.py
pyfaktory/consumer.py
pyfaktory/models.py
pyfaktory/producer.py
pyfaktory/util/__init__.py
pyfaktory/util/constants.py
pyfaktory/util/decorators.py
pyfaktory/util/enums.py
pyfaktory/util/exceptions.py
pyfaktory/util/helper.py
pyfaktory-0.2.10.dist-info/LICENSE.md
pyfaktory-0.2.10.dist-info/METADATA
pyfaktory-0.2.10.dist-info/WHEEL
pyfaktory-0.2.10.dist-info/RECORD
