Metadata-Version: 2.1
Name: pyfaktory
Version: 0.2.10
Summary: Faktory Client Python (Producer and Consumer/Worker)
Home-page: https://github.com/ghilesmeddour/faktory_worker_python
License: MIT
Author: Ghiles Meddour
Author-email: ghiles.meddour.b@gmail.com
Requires-Python: >=3.9,<4.0
Classifier: License :: OSI Approved :: MIT License
Classifier: Operating System :: OS Independent
Classifier: Programming Language :: Python :: 3
Classifier: Programming Language :: Python :: 3.9
Classifier: Programming Language :: Python :: 3.10
Classifier: Programming Language :: Python :: 3.11
Classifier: Programming Language :: Python :: 3.12
Provides-Extra: sentry
Requires-Dist: Pebble (>=5.0.5,<6.0.0)
Requires-Dist: pydantic (>=2.5.2,<3.0.0)
Requires-Dist: rfc3339-validator (>=0.1.4,<0.2.0)
Project-URL: Documentation, https://github.com/ghilesmeddour/faktory_worker_python
Project-URL: Repository, https://github.com/ghilesmeddour/faktory_worker_python
